pandas_ods_reader/__init__.py
pandas_ods_reader/algo.py
pandas_ods_reader/main.py
pandas_ods_reader/parsers/fods.py
pandas_ods_reader/parsers/ods.py
pandas_ods_reader/py.typed
pandas_ods_reader/utils.py
pandas_ods_reader-1.0.2.dist-info/LICENSE.txt
pandas_ods_reader-1.0.2.dist-info/METADATA
pandas_ods_reader-1.0.2.dist-info/WHEEL
pandas_ods_reader-1.0.2.dist-info/RECORD
