Metadata-Version: 2.3
Name: pandas-ods-reader
Version: 1.0.2
Summary: Read in .ods and .fods files and return a pandas.DataFrame.
License: MIT
Keywords: data,io,pandas,ods
Author: iuvbio
Author-email: iuvbio@users.noreply.github.com
Requires-Python: >=3.9,<4
Classifier: Development Status :: 5 - Production/Stable
Classifier: License :: OSI Approved :: MIT License
Classifier: Programming Language :: Python :: 3
Classifier: Programming Language :: Python :: 3.9
Classifier: Programming Language :: Python :: 3.10
Classifier: Programming Language :: Python :: 3.11
Classifier: Programming Language :: Python :: 3.12
Classifier: Programming Language :: Python :: 3.13
Classifier: Topic :: Utilities
Requires-Dist: ezodf (>=0.3.2)
Requires-Dist: lxml (>=4.9.2)
Requires-Dist: pandas (>=2.2.3)
Project-URL: Repository, https://github.com/iuvbio/pandas_ods_reader
